financial_calculator/__init__.py
financial_calculator/__main__.py
financial_calculator/calculations.py
financial_calculator_vtcu-0.1.0.dist-info/METADATA
financial_calculator_vtcu-0.1.0.dist-info/WHEEL
financial_calculator_vtcu-0.1.0.dist-info/entry_points.txt
financial_calculator_vtcu-0.1.0.dist-info/top_level.txt
financial_calculator_vtcu-0.1.0.dist-info/RECORD
