Metadata-Version: 2.1
Name: financial-calculator-vtcu
Version: 0.1.0
Summary: Пакет для расчёта чистой прибыли и рентабельности инвестиций (ROI)
Author: vtcu
Author-email: sleeve_thinker_0d@icloud.com
Classifier: Programming Language :: Python :: 3
Classifier: License :: OSI Approved :: MIT License
Classifier: Operating System :: OS Independent
Requires-Python: >=3.8
